LICENSE
README.md
setup.py
cloudmersive_fraud_detection_api_client/__init__.py
cloudmersive_fraud_detection_api_client/api_client.py
cloudmersive_fraud_detection_api_client/configuration.py
cloudmersive_fraud_detection_api_client/rest.py
cloudmersive_fraud_detection_api_client.egg-info/PKG-INFO
cloudmersive_fraud_detection_api_client.egg-info/SOURCES.txt
cloudmersive_fraud_detection_api_client.egg-info/dependency_links.txt
cloudmersive_fraud_detection_api_client.egg-info/requires.txt
cloudmersive_fraud_detection_api_client.egg-info/top_level.txt
cloudmersive_fraud_detection_api_client/api/__init__.py
cloudmersive_fraud_detection_api_client/api/fraud_detection_api.py
cloudmersive_fraud_detection_api_client/models/__init__.py
cloudmersive_fraud_detection_api_client/models/advanced_fraud_detection_result.py
cloudmersive_fraud_detection_api_client/models/fraud_detection_result.py
test/__init__.py
test/test_advanced_fraud_detection_result.py
test/test_fraud_detection_api.py
test/test_fraud_detection_result.py