Metadata-Version: 2.4
Name: cloudmersive_fraud_detection_api_client
Version: 3.0.0
Summary: fraudapi
Home-page: https://cloudmersive.com/ai-fraud-detection-api
Author-email: 
Keywords: Swagger,fraudapi
License-File: LICENSE
Requires-Dist: certifi>=2017.4.17
Requires-Dist: python-dateutil>=2.1
Requires-Dist: six>=1.10
Requires-Dist: urllib3>=1.23
Dynamic: description
Dynamic: description-content-type
Dynamic: home-page
Dynamic: keywords
Dynamic: license-file
Dynamic: requires-dist
Dynamic: summary
